seastats/__init__.py
seastats/py.typed
seastats/stats.py
seastats/storms.py
seastats-0.1.2.dist-info/LICENSE
seastats-0.1.2.dist-info/METADATA
seastats-0.1.2.dist-info/WHEEL
seastats-0.1.2.dist-info/RECORD
